ottopy/__init__.py
ottopy/_frontend.py
ottopy/_version.py
ottopy/example.py
ottopy/lib.py
ottopy/maze.py
ottopy/robot.py
ottopy/labextension/build_log.json
ottopy/labextension/install.json
ottopy/labextension/package.json
ottopy/labextension/static/102.850c01c7c484f53226e5.js
ottopy/labextension/static/367.7b39d712b26fff263fe2.js
ottopy/labextension/static/367.b62986d1f8caa065da16.js
ottopy/labextension/static/480.f2598c864872810028ca.js
ottopy/labextension/static/568.1f767b1f0d8143da2491.js
ottopy/labextension/static/781.9720a4821780eb68ece3.js
ottopy/labextension/static/809.b75bc51ac84fb202247a.js
ottopy/labextension/static/809.b75bc51ac84fb202247a.js.LICENSE.txt
ottopy/labextension/static/lib_index_js.22f27009b850fa0a4117.js
ottopy/labextension/static/lib_index_js.22f27009b850fa0a4117.js.map
ottopy/labextension/static/lib_plugin_js.165252e0da2903b5fcaf.js
ottopy/labextension/static/lib_plugin_js.165252e0da2903b5fcaf.js.map
ottopy/labextension/static/lib_widget_js.66e79b574d5e8fbe8cdf.js
ottopy/labextension/static/lib_widget_js.66e79b574d5e8fbe8cdf.js.map
ottopy/labextension/static/lib_widget_js.82adc3febd787308c795.js
ottopy/labextension/static/lib_widget_js.82adc3febd787308c795.js.map
ottopy/labextension/static/remoteEntry.21401f21d0fcf260cecd.js
ottopy/labextension/static/remoteEntry.46c29ca21d5b16a156ac.js
ottopy/labextension/static/remoteEntry.46c29ca21d5b16a156ac.js.map
ottopy/labextension/static/remoteEntry.5cdf2070acb39f91773a.js
ottopy/labextension/static/remoteEntry.5cdf2070acb39f91773a.js.map
ottopy/labextension/static/remoteEntry.6a4865e09bed49ba34ab.js
ottopy/labextension/static/style.js
ottopy/labextension/static/third-party-licenses.json
ottopy/labextension/static/vendors-node_modules_css-loader_dist_runtime_api_js-node_modules_jquery_dist_jquery_js-node_m-d60a54.368d38490f83d0758486.js
ottopy/labextension/static/vendors-node_modules_css-loader_dist_runtime_api_js-node_modules_jquery_dist_jquery_js-node_m-d60a54.368d38490f83d0758486.js.map
ottopy-0.1.21.dist-info/LICENSE.txt
ottopy-0.1.21.dist-info/METADATA
ottopy-0.1.21.dist-info/WHEEL
ottopy-0.1.21.dist-info/top_level.txt
ottopy-0.1.21.dist-info/RECORD
